CHANGES.rst
LICENSE.txt
MANIFEST.in
README.rst
setup.cfg
setup.py
TracAuthOpenId.egg-info/PKG-INFO
TracAuthOpenId.egg-info/SOURCES.txt
TracAuthOpenId.egg-info/dependency_links.txt
TracAuthOpenId.egg-info/entry_points.txt
TracAuthOpenId.egg-info/requires.txt
TracAuthOpenId.egg-info/top_level.txt
authopenid/__init__.py
authopenid/authopenid.py
authopenid/htdocs/css/openid.css
authopenid/htdocs/images/aol.gif
authopenid/htdocs/images/blogger.ico
authopenid/htdocs/images/claimid.ico
authopenid/htdocs/images/facebook.gif
authopenid/htdocs/images/flickr.ico
authopenid/htdocs/images/google.gif
authopenid/htdocs/images/livejournal.ico
authopenid/htdocs/images/myopenid.ico
authopenid/htdocs/images/openid-inputicon.gif
authopenid/htdocs/images/openid.gif
authopenid/htdocs/images/technorati.ico
authopenid/htdocs/images/verisign.ico
authopenid/htdocs/images/vidoop.ico
authopenid/htdocs/images/wordpress.ico
authopenid/htdocs/images/yahoo.gif
authopenid/htdocs/js/openid-jquery.js
authopenid/templates/autosubmitform.html
authopenid/templates/openidlogin.html