Metadata-Version: 1.0
Name: TracAuthOpenId
Version: 0.4.4
Summary: OpenID plugin for Trac
Home-page: https://github.com/dairiki/authopenid-plugin/
Author: Jeff Dairiki
Author-email: dairiki@dairiki.org
License: Trac license (BSD-like)
Keywords: trac openid
Platform: Any
Classifier: Development Status :: 4 - Beta
Classifier: Environment :: Plugins
Classifier: Environment :: Web Environment
Classifier: Framework :: Trac
Classifier: Intended Audience :: System Administrators
Classifier: Topic :: Internet :: WWW/HTTP
Classifier: Programming Language :: Python :: 2
Classifier: License :: OSI Approved :: BSD License
